solaxx3/__init__.py
solaxx3/solax_registers_info.py
solaxx3/solaxx3.py
solaxx3/utils.py
solaxx3-1.0.5.dist-info/licenses/LICENSE
solaxx3-1.0.5.dist-info/METADATA
solaxx3-1.0.5.dist-info/WHEEL
solaxx3-1.0.5.dist-info/top_level.txt
solaxx3-1.0.5.dist-info/RECORD
