Metadata-Version: 2.4
Name: solaxx3
Version: 1.0.5
Summary: Read Solax X3 inverter registers via modbus interface (RS-485)
Author-email: Flavius Moldovan <mkfam@protonmail.com>, Philip Moldovan <phdfam@protonmail.com>
License-Expression: MIT
Project-URL: Homepage, https://github.com/mkfam7/solaxx3
Project-URL: Issues, https://github.com/mkfam7/solaxx3/issues
Keywords: Solax,solax-x3,solaxx3,solar inverter,RTU,MODBUS
Classifier: Operating System :: OS Independent
Classifier: Programming Language :: Python
Classifier: Programming Language :: Python :: 3
Classifier: Programming Language :: Python :: 3.8
Classifier: Programming Language :: Python :: 3.9
Classifier: Programming Language :: Python :: 3.10
Classifier: Programming Language :: Python :: 3.11
Classifier: Programming Language :: Python :: 3.12
Classifier: Programming Language :: Python :: 3.13
Classifier: Programming Language :: Python :: 3.14
Requires-Python: >=3.8
License-File: LICENSE
Requires-Dist: pymodbus[serial]<3.12.0,>=3.0.0
Dynamic: license-file
